ldr/modelling/__init__.py
ldr/modelling/camel.py
ldr/modelling/pascal.py
ldr/modelling/snake.py
ldr/modelling/bigquery/__init__.py
ldr/modelling/bigquery/errors.py
ldr/modelling/bigquery/model.py
ldr/modelling/bigquery/types/__init__.py
ldr/modelling/bigquery/types/bignumeric.py
ldr/modelling/bigquery/types/geography.py
ldr/modelling/bigquery/types/numeric.py
ldr/modelling/bigquery/types/timestamp.py
ldr_modelling-0.2.1.dist-info/METADATA
ldr_modelling-0.2.1.dist-info/WHEEL
ldr_modelling-0.2.1.dist-info/RECORD
