Metadata-Version: 2.4
Name: ldr-modelling
Version: 0.2.1
Summary: Pydantic helpers to inherit from when modelling data.
Author-email: Louder <devops@louder.com.au>
Requires-Python: >=3.12
Requires-Dist: pydantic>=2.0
Requires-Dist: shapely>=2.0
